dare_datasets/__init__.py
dare_datasets/dataset_abc.py
dare_datasets/iris.py
dare_datasets/processing/__init__.py
dare_datasets/processing/qr2t_benchmark/__init__.py
dare_datasets/processing/qr2t_benchmark/qr2t_to_totto.py
dare_datasets/processing/qr2t_benchmark/totto_to_concise_input.py
dare_datasets/processing/spider/__init__.py
dare_datasets/processing/spider/dealiasing.py
dare_datasets/processing/spider/execute_sqlite_query.py
dare_datasets/processing/spider/lower.py
dare_datasets/processing/spider/serialize_schema.py
dare_datasets/processing/totto/__init__.py
dare_datasets/processing/totto/preprocessing_utils.py
dare_datasets/processing/totto/totto_to_serialized.py
dare_datasets/processing/wikidata/__init__.py
dare_datasets/processing/wikidata/simplify_schema.py
dare_datasets/qr2t_benchmark.py
dare_datasets/repositories/__init__.py
dare_datasets/repositories/huggingface.py
dare_datasets/spider.py
dare_datasets/totto.py
dare_datasets/utils/__init__.py
dare_datasets/utils/require_files.py
dare_datasets/utils/unzip.py
dare_datasets/wikitable.py
dare_datasets-1.0.1.dist-info/METADATA
dare_datasets-1.0.1.dist-info/WHEEL
dare_datasets-1.0.1.dist-info/RECORD
