Metadata-Version: 2.1
Name: dare-datasets
Version: 1.0.1
Summary: A quick and easy way to download datasets from the DARE lab.
License: MIT
Author: MikeXydas
Author-email: mikexydas@gmail.com
Requires-Python: >=3.8,<4.0
Classifier: License :: OSI Approved :: MIT License
Classifier: Programming Language :: Python :: 3
Classifier: Programming Language :: Python :: 3.8
Classifier: Programming Language :: Python :: 3.9
Classifier: Programming Language :: Python :: 3.10
Classifier: Programming Language :: Python :: 3.11
Requires-Dist: huggingface-hub (>=0.17.1,<0.18.0)
Requires-Dist: mo-sql-parsing (==5.58.21262)
Requires-Dist: numpy (>=1.24.3,<2.0.0)
Requires-Dist: pandas (>=2.0.2,<3.0.0)
Requires-Dist: requests (>=2.31.0,<3.0.0)
Requires-Dist: sql-metadata (>=2.9.0,<3.0.0)
Requires-Dist: sqlparse (>=0.4.4,<0.5.0)
Project-URL: Documentation, https://darelab.athenarc.gr/datasets-docs/
